[
  {
    "tower": "Stockade",
    "lat": 48.88499183447564,
    "lng": -123.36154332598294
  },
  {
    "tower": "Winstanley",
    "lat": 48.87371779366148,
    "lng": -123.33240051077976
  },
  {
    "tower": "Madrona",
    "lat": 48.969315952069024,
    "lng": -123.55463183817622
  },
  {
    "tower": "Pattison",
    "lat": 48.88956906987449,
    "lng": -123.36491857693203
  },
  {
    "tower": "Therah",
    "lat": 48.99693380879938,
    "lng": -123.56736551553075
  },
  {
    "tower": "Vineyard",
    "lat": 48.947676207243454,
    "lng": -123.50478713298459
  },
  {
    "tower": "Quadra",
    "lat": 48.934757958736,
    "lng": -123.47083546795885
  },
  {
    "tower": "Parker",
    "lat": 48.887584683568726,
    "lng": -123.41690479703237
  },
  {
    "tower": "Georgia View",
    "lat": 48.90489366286939,
    "lng": -123.37742072351277
  },
  {
    "tower": "Bluff Rd W",
    "lat": 48.873261827312966,
    "lng": -123.34671676147973
  },
  {
    "tower": "Highland",
    "lat": 48.868784080507375,
    "lng": -123.34599037771828
  },
  {
    "tower": "Whaler",
    "lat": 48.88613745583038,
    "lng": -123.32417551072722
  },
  {
    "tower": "Gossip",
    "lat": 48.89417232913687,
    "lng": -123.32359987674648
  },
  {
    "tower": "Warbler",
    "lat": 48.87711866422133,
    "lng": -123.33224574373405
  },
  {
    "tower": "Devina",
    "lat": 48.991340539684266,
    "lng": -123.5724144523506
  },
  {
    "tower": "Zitka",
    "lat": 48.97382243519875,
    "lng": -123.5621428465889
  },
  {
    "tower": "Clanton",
    "lat": 48.8972191796034,
    "lng": -123.3965053720802
  }
]
